ioc.py
django_postgres_ioc-0.0.2.dist-info/METADATA
django_postgres_ioc-0.0.2.dist-info/RECORD
django_postgres_ioc-0.0.2.dist-info/WHEEL
django_postgres_ioc-0.0.2.dist-info/top_level.txt
