Metadata-Version: 2.1
Name: django-postgres-ioc
Version: 0.0.2
Summary: A Django model manager providing insert on conflict for PostgreSQL database tables.
Home-page: http://github.com/luojilab/django-postgres-ioc
Author: mrgaolei
Author-email: gaolei@luojilab.com
License: UNKNOWN
Platform: UNKNOWN
Classifier: Development Status :: 5 - Production/Stable
Classifier: Environment :: Web Environment
Classifier: Intended Audience :: Developers
Classifier: Operating System :: OS Independent
Classifier: Programming Language :: Python
Classifier: Programming Language :: Python :: 2.6
Classifier: Programming Language :: Python :: 2.7
Classifier: Programming Language :: Python :: 3
Classifier: Programming Language :: Python :: 3.3
Classifier: Framework :: Django
Classifier: Topic :: Internet :: WWW/HTTP :: Dynamic Content
Classifier: Topic :: Internet :: WWW/HTTP :: Site Management
Requires-Dist: django (>=1.7)
